kgexplore/__init__.py
kgexplore/client.py
kgexplore/configurations.py
kgexplore/visual.py
kgexplore/resources/watermark.png
kgexplore/resources/simhei/simhei.ttf
kgexplore-0.1.2.dist-info/LICENSE
kgexplore-0.1.2.dist-info/METADATA
kgexplore-0.1.2.dist-info/WHEEL
kgexplore-0.1.2.dist-info/top_level.txt
kgexplore-0.1.2.dist-info/RECORD
