Metadata-Version: 2.1
Name: kgexplore
Version: 0.1.2
Summary: Python Package for Knowledge Exploration
Home-page: https://github.com/smoothnlp/kgexplore
Author: SmoothNLP Organization
Author-email: contact@smoothnlp.com
License: UNKNOWN
Keywords: Knowledge Graph,Business
Platform: UNKNOWN
Classifier: Programming Language :: Python :: 3
Classifier: License :: OSI Approved :: MIT License
Classifier: Operating System :: OS Independent
Requires-Dist: request
